{
  "Notes": [
    {
      "Paper": 11,
      "Section": 0,
      "Paragraph": 0,
      "TranslatorNote": "",
      "Notes": "",
      "LastDate": "2013-07-16T11:34:06.193",
      "Status": 1,
      "Format": 1
    },
    {
      "Paper": 11,
      "Section": 0,
      "Paragraph": 1,
      "TranslatorNote": "",
      "Notes": "",
      "LastDate": "2023-04-04T18:43:54.1525407Z",
      "Status": 3,
      "Format": 0
    },
    {
      "Paper": 11,
      "Section": 0,
      "Paragraph": 2,
      "TranslatorNote": "",
      "Notes": "",
      "LastDate": "2022-07-30T18:32:24.923",
      "Status": 1,
      "Format": 3
    },
    {
      "Paper": 11,
      "Section": 1,
      "Paragraph": 0,
      "TranslatorNote": "",
      "Notes": "",
      "LastDate": "2013-07-16T11:34:06.217",
      "Status": 3,
      "Format": 2
    },
    {
      "Paper": 11,
      "Section": 1,
      "Paragraph": 1,
      "TranslatorNote": "",
      "Notes": "Surround (ed) = cercar, rodear, circundar.",
      "LastDate": "2022-07-30T18:32:24.923",
      "Status": 1,
      "Format": 3
    },
    {
      "Paper": 11,
      "Section": 1,
      "Paragraph": 2,
      "TranslatorNote": "",
      "Notes": "",
      "LastDate": "2022-07-30T18:32:24.923",
      "Status": 1,
      "Format": 3
    },
    {
      "Paper": 11,
      "Section": 1,
      "Paragraph": 3,
      "TranslatorNote": "",
      "Notes": "",
      "LastDate": "2022-07-30T18:32:24.923",
      "Status": 1,
      "Format": 3
    },
    {
      "Paper": 11,
      "Section": 1,
      "Paragraph": 4,
      "TranslatorNote": "",
      "Notes": "",
      "LastDate": "2022-07-30T18:32:24.923",
      "Status": 1,
      "Format": 3
    },
    {
      "Paper": 11,
      "Section": 2,
      "Paragraph": 0,
      "TranslatorNote": "",
      "Notes": "",
      "LastDate": "2013-07-16T11:34:06.25",
      "Status": 1,
      "Format": 2
    },
    {
      "Paper": 11,
      "Section": 2,
      "Paragraph": 1,
      "TranslatorNote": "",
      "Notes": "",
      "LastDate": "2013-07-16T11:34:06.257",
      "Status": 1,
      "Format": 3
    },
    {
      "Paper": 11,
      "Section": 2,
      "Paragraph": 2,
      "TranslatorNote": "",
      "Notes": "",
      "LastDate": "2013-07-16T11:34:06.263",
      "Status": 1,
      "Format": 3
    },
    {
      "Paper": 11,
      "Section": 2,
      "Paragraph": 3,
      "TranslatorNote": "",
      "Notes": "",
      "LastDate": "2013-07-16T11:34:06.273",
      "Status": 1,
      "Format": 3
    },
    {
      "Paper": 11,
      "Section": 2,
      "Paragraph": 4,
      "TranslatorNote": "",
      "Notes": "",
      "LastDate": "2013-07-16T11:34:06.28",
      "Status": 1,
      "Format": 3
    },
    {
      "Paper": 11,
      "Section": 2,
      "Paragraph": 5,
      "TranslatorNote": "",
      "Notes": "",
      "LastDate": "2013-07-16T11:34:06.287",
      "Status": 1,
      "Format": 4
    },
    {
      "Paper": 11,
      "Section": 2,
      "Paragraph": 6,
      "TranslatorNote": "",
      "Notes": "",
      "LastDate": "2013-07-16T11:34:06.293",
      "Status": 1,
      "Format": 4
    },
    {
      "Paper": 11,
      "Section": 2,
      "Paragraph": 7,
      "TranslatorNote": "",
      "Notes": "",
      "LastDate": "2013-07-16T11:34:06.3",
      "Status": 1,
      "Format": 4
    },
    {
      "Paper": 11,
      "Section": 2,
      "Paragraph": 8,
      "TranslatorNote": "",
      "Notes": "",
      "LastDate": "2013-07-16T11:34:06.307",
      "Status": 1,
      "Format": 3
    },
    {
      "Paper": 11,
      "Section": 2,
      "Paragraph": 9,
      "TranslatorNote": "",
      "Notes": "",
      "LastDate": "2023-04-04T18:45:36.2965739Z",
      "Status": 3,
      "Format": 0
    },
    {
      "Paper": 11,
      "Section": 2,
      "Paragraph": 10,
      "TranslatorNote": "",
      "Notes": "",
      "LastDate": "2013-07-16T11:34:06.32",
      "Status": 1,
      "Format": 3
    },
    {
      "Paper": 11,
      "Section": 2,
      "Paragraph": 11,
      "TranslatorNote": "",
      "Notes": "",
      "LastDate": "2013-07-16T11:34:06.33",
      "Status": 1,
      "Format": 3
    },
    {
      "Paper": 11,
      "Section": 3,
      "Paragraph": 0,
      "TranslatorNote": "",
      "Notes": "",
      "LastDate": "2013-07-16T11:34:06.337",
      "Status": 1,
      "Format": 2
    },
    {
      "Paper": 11,
      "Section": 3,
      "Paragraph": 1,
      "TranslatorNote": "",
      "Notes": "Proponho as seguintes tradu\u00E7\u00F5es para os termos:\r\n\r\nThe Most Holy Sphere- A Mais Sagrada Esfera OU A Esfera Mais Sagrada em vez de Esfera Sant\u00EDssima.\r\nHoly Area - \u00C1rea Sagrada em vez de \u00C1rea Santa.",
      "LastDate": "2023-04-04T18:47:06.0774319Z",
      "Status": 3,
      "Format": 0
    },
    {
      "Paper": 11,
      "Section": 3,
      "Paragraph": 2,
      "TranslatorNote": "",
      "Notes": "\u00C1rea Santa. No original \u00E9 Terra Santa (Holy Land). Trata-se, no caso, de recorda\u00E7\u00F5es dos dias materiais, \u00E1reas de reminisc\u00EAncias hist\u00F3ricas.  Repensemos.",
      "LastDate": "2022-07-30T18:32:24.923",
      "Status": 1,
      "Format": 3
    },
    {
      "Paper": 11,
      "Section": 3,
      "Paragraph": 3,
      "TranslatorNote": "",
      "Notes": "\u00C1rea Santa - Holy Area (\u00C1rea Sagrada) Vide sugest\u00E3o anterior.",
      "LastDate": "2022-07-30T18:32:24.923",
      "Status": 1,
      "Format": 3
    },
    {
      "Paper": 11,
      "Section": 3,
      "Paragraph": 4,
      "TranslatorNote": "",
      "Notes": "",
      "LastDate": "2022-07-30T18:32:24.923",
      "Status": 1,
      "Format": 3
    },
    {
      "Paper": 11,
      "Section": 4,
      "Paragraph": 0,
      "TranslatorNote": "",
      "Notes": "",
      "LastDate": "2013-07-16T11:34:06.37",
      "Status": 1,
      "Format": 2
    },
    {
      "Paper": 11,
      "Section": 4,
      "Paragraph": 1,
      "TranslatorNote": "",
      "Notes": "",
      "LastDate": "2022-07-30T18:32:24.923",
      "Status": 1,
      "Format": 3
    },
    {
      "Paper": 11,
      "Section": 4,
      "Paragraph": 2,
      "TranslatorNote": "",
      "Notes": "Flash j\u00E1 se encontra no Aur\u00E9lio, como clar\u00E3o r\u00E1pido e intenso capaz de fornecer luz. Neste texto, se houvesse acordo un\u00E2nime dos tradutores, talvez pud\u00E9ssemos traduzir flash por clar\u00E3o, ou deixar flash (esta\u00E7\u00F5es de flash).\r\nSugeri \u0022....esta\u00E7\u00F5es de jatos de luz\u0022  que, no meu entendimento, caracteriza bem as \u0022flash stations.\u0022 Pensei tamb\u00E9m em ...esta\u00E7\u00F5es de sinal luminoso para determinadas energias do Para\u00EDso que se dirigem para .......\r\n\r\nE o ali (here ?) Here \u00E9 aqui, como sabemos.",
      "LastDate": "2022-07-30T18:32:24.923",
      "Status": 1,
      "Format": 3
    },
    {
      "Paper": 11,
      "Section": 4,
      "Paragraph": 3,
      "TranslatorNote": "",
      "Notes": "",
      "LastDate": "2013-07-16T11:34:06.39",
      "Status": 1,
      "Format": 3
    },
    {
      "Paper": 11,
      "Section": 4,
      "Paragraph": 4,
      "TranslatorNote": "",
      "Notes": "",
      "LastDate": "2013-07-16T11:34:06.4",
      "Status": 1,
      "Format": 3
    },
    {
      "Paper": 11,
      "Section": 4,
      "Paragraph": 5,
      "TranslatorNote": "",
      "Notes": "",
      "LastDate": "2013-07-16T11:34:06.407",
      "Status": 1,
      "Format": 3
    },
    {
      "Paper": 11,
      "Section": 5,
      "Paragraph": 0,
      "TranslatorNote": "",
      "Notes": "",
      "LastDate": "2013-07-16T11:34:06.413",
      "Status": 1,
      "Format": 2
    },
    {
      "Paper": 11,
      "Section": 5,
      "Paragraph": 1,
      "TranslatorNote": "",
      "Notes": "",
      "LastDate": "2013-07-16T11:34:06.42",
      "Status": 1,
      "Format": 3
    },
    {
      "Paper": 11,
      "Section": 5,
      "Paragraph": 2,
      "TranslatorNote": "",
      "Notes": "",
      "LastDate": "2013-07-16T11:34:06.427",
      "Status": 1,
      "Format": 4
    },
    {
      "Paper": 11,
      "Section": 5,
      "Paragraph": 3,
      "TranslatorNote": "",
      "Notes": "",
      "LastDate": "2013-07-16T11:34:06.433",
      "Status": 1,
      "Format": 4
    },
    {
      "Paper": 11,
      "Section": 5,
      "Paragraph": 4,
      "TranslatorNote": "",
      "Notes": "",
      "LastDate": "2013-07-16T11:34:06.44",
      "Status": 1,
      "Format": 4
    },
    {
      "Paper": 11,
      "Section": 5,
      "Paragraph": 5,
      "TranslatorNote": "",
      "Notes": "",
      "LastDate": "2023-04-04T18:47:40.3116303Z",
      "Status": 3,
      "Format": 0
    },
    {
      "Paper": 11,
      "Section": 5,
      "Paragraph": 6,
      "TranslatorNote": "",
      "Notes": "",
      "LastDate": "2023-04-04T18:49:52.6337304Z",
      "Status": 3,
      "Format": 0
    },
    {
      "Paper": 11,
      "Section": 5,
      "Paragraph": 7,
      "TranslatorNote": "",
      "Notes": "",
      "LastDate": "2023-04-04T18:50:09.5053713Z",
      "Status": 3,
      "Format": 0
    },
    {
      "Paper": 11,
      "Section": 5,
      "Paragraph": 8,
      "TranslatorNote": "",
      "Notes": "Sugest\u00E3o: 4a. ora\u00E7\u00E3o..... a for\u00E7a espacial sai...........(ou deixa o centro)......... entra.",
      "LastDate": "2022-07-30T18:32:24.923",
      "Status": 1,
      "Format": 3
    },
    {
      "Paper": 11,
      "Section": 5,
      "Paragraph": 9,
      "TranslatorNote": "",
      "Notes": "",
      "LastDate": "2013-07-16T11:34:06.477",
      "Status": 1,
      "Format": 3
    },
    {
      "Paper": 11,
      "Section": 6,
      "Paragraph": 0,
      "TranslatorNote": "",
      "Notes": "",
      "LastDate": "2013-07-16T11:34:06.483",
      "Status": 1,
      "Format": 2
    },
    {
      "Paper": 11,
      "Section": 6,
      "Paragraph": 1,
      "TranslatorNote": "",
      "Notes": "",
      "LastDate": "2013-07-16T11:34:06.49",
      "Status": 1,
      "Format": 3
    },
    {
      "Paper": 11,
      "Section": 6,
      "Paragraph": 2,
      "TranslatorNote": "",
      "Notes": "",
      "LastDate": "2013-07-16T11:34:06.497",
      "Status": 1,
      "Format": 3
    },
    {
      "Paper": 11,
      "Section": 6,
      "Paragraph": 3,
      "TranslatorNote": "",
      "Notes": "",
      "LastDate": "2013-07-16T11:34:06.503",
      "Status": 1,
      "Format": 3
    },
    {
      "Paper": 11,
      "Section": 6,
      "Paragraph": 4,
      "TranslatorNote": "",
      "Notes": "",
      "LastDate": "2013-07-16T11:34:06.51",
      "Status": 1,
      "Format": 3
    },
    {
      "Paper": 11,
      "Section": 6,
      "Paragraph": 5,
      "TranslatorNote": "",
      "Notes": "",
      "LastDate": "2013-07-16T11:34:06.52",
      "Status": 1,
      "Format": 3
    },
    {
      "Paper": 11,
      "Section": 7,
      "Paragraph": 0,
      "TranslatorNote": "",
      "Notes": "",
      "LastDate": "2013-07-16T11:34:06.527",
      "Status": 1,
      "Format": 2
    },
    {
      "Paper": 11,
      "Section": 7,
      "Paragraph": 1,
      "TranslatorNote": "",
      "Notes": "",
      "LastDate": "2023-04-04T18:52:55.0949089Z",
      "Status": 3,
      "Format": 0
    },
    {
      "Paper": 11,
      "Section": 7,
      "Paragraph": 2,
      "TranslatorNote": "",
      "Notes": "",
      "LastDate": "2013-07-16T11:34:06.54",
      "Status": 1,
      "Format": 3
    },
    {
      "Paper": 11,
      "Section": 7,
      "Paragraph": 3,
      "TranslatorNote": "",
      "Notes": "The vertical cross section ( A \u0022sec\u00E7\u00E3o\u0022 de um corte vertical) ???\r\n\r\n",
      "LastDate": "2022-07-30T18:32:24.923",
      "Status": 1,
      "Format": 3
    },
    {
      "Paper": 11,
      "Section": 7,
      "Paragraph": 4,
      "TranslatorNote": "",
      "Notes": "",
      "LastDate": "2013-07-16T11:34:06.553",
      "Status": 1,
      "Format": 3
    },
    {
      "Paper": 11,
      "Section": 7,
      "Paragraph": 5,
      "TranslatorNote": "",
      "Notes": "",
      "LastDate": "2013-07-16T11:34:06.56",
      "Status": 1,
      "Format": 3
    },
    {
      "Paper": 11,
      "Section": 7,
      "Paragraph": 6,
      "TranslatorNote": "",
      "Notes": "",
      "LastDate": "2013-07-16T11:34:06.567",
      "Status": 1,
      "Format": 3
    },
    {
      "Paper": 11,
      "Section": 7,
      "Paragraph": 7,
      "TranslatorNote": "",
      "Notes": "",
      "LastDate": "2013-07-16T11:34:06.573",
      "Status": 1,
      "Format": 3
    },
    {
      "Paper": 11,
      "Section": 7,
      "Paragraph": 8,
      "TranslatorNote": "",
      "Notes": "",
      "LastDate": "2013-07-16T11:34:06.583",
      "Status": 1,
      "Format": 3
    },
    {
      "Paper": 11,
      "Section": 7,
      "Paragraph": 9,
      "TranslatorNote": "",
      "Notes": "",
      "LastDate": "2013-07-16T11:34:06.59",
      "Status": 1,
      "Format": 3
    },
    {
      "Paper": 11,
      "Section": 8,
      "Paragraph": 0,
      "TranslatorNote": "",
      "Notes": "",
      "LastDate": "2013-07-16T11:34:06.597",
      "Status": 1,
      "Format": 2
    },
    {
      "Paper": 11,
      "Section": 8,
      "Paragraph": 1,
      "TranslatorNote": "",
      "Notes": "",
      "LastDate": "2013-07-16T11:34:06.603",
      "Status": 1,
      "Format": 3
    },
    {
      "Paper": 11,
      "Section": 8,
      "Paragraph": 2,
      "TranslatorNote": "",
      "Notes": "",
      "LastDate": "2013-07-16T11:34:06.61",
      "Status": 1,
      "Format": 3
    },
    {
      "Paper": 11,
      "Section": 8,
      "Paragraph": 3,
      "TranslatorNote": "",
      "Notes": "",
      "LastDate": "2013-07-16T11:34:06.617",
      "Status": 1,
      "Format": 3
    },
    {
      "Paper": 11,
      "Section": 8,
      "Paragraph": 4,
      "TranslatorNote": "",
      "Notes": "",
      "LastDate": "2013-07-16T11:34:06.623",
      "Status": 1,
      "Format": 3
    },
    {
      "Paper": 11,
      "Section": 8,
      "Paragraph": 5,
      "TranslatorNote": "",
      "Notes": "",
      "LastDate": "2023-04-04T18:54:47.9022609Z",
      "Status": 3,
      "Format": 0
    },
    {
      "Paper": 11,
      "Section": 8,
      "Paragraph": 6,
      "TranslatorNote": "",
      "Notes": "",
      "LastDate": "2023-04-05T06:30:35.1365946Z",
      "Status": 3,
      "Format": 0
    },
    {
      "Paper": 11,
      "Section": 8,
      "Paragraph": 7,
      "TranslatorNote": "",
      "Notes": "",
      "LastDate": "2023-04-05T06:29:56.9515193Z",
      "Status": 3,
      "Format": 0
    },
    {
      "Paper": 11,
      "Section": 8,
      "Paragraph": 8,
      "TranslatorNote": "",
      "Notes": "",
      "LastDate": "2013-07-16T11:34:06.653",
      "Status": 1,
      "Format": 3
    },
    {
      "Paper": 11,
      "Section": 8,
      "Paragraph": 9,
      "TranslatorNote": "",
      "Notes": "",
      "LastDate": "2013-07-16T11:34:06.66",
      "Status": 1,
      "Format": 3
    },
    {
      "Paper": 11,
      "Section": 9,
      "Paragraph": 0,
      "TranslatorNote": "",
      "Notes": "",
      "LastDate": "2013-07-16T11:34:06.667",
      "Status": 1,
      "Format": 2
    },
    {
      "Paper": 11,
      "Section": 9,
      "Paragraph": 1,
      "TranslatorNote": "",
      "Notes": "",
      "LastDate": "2013-07-16T11:34:06.673",
      "Status": 1,
      "Format": 3
    },
    {
      "Paper": 11,
      "Section": 9,
      "Paragraph": 2,
      "TranslatorNote": "",
      "Notes": "",
      "LastDate": "2013-07-16T11:34:06.68",
      "Status": 1,
      "Format": 3
    },
    {
      "Paper": 11,
      "Section": 9,
      "Paragraph": 3,
      "TranslatorNote": "",
      "Notes": "",
      "LastDate": "2013-07-16T11:34:06.687",
      "Status": 1,
      "Format": 3
    },
    {
      "Paper": 11,
      "Section": 9,
      "Paragraph": 4,
      "TranslatorNote": "",
      "Notes": "",
      "LastDate": "2013-07-16T11:34:06.693",
      "Status": 1,
      "Format": 3
    },
    {
      "Paper": 11,
      "Section": 9,
      "Paragraph": 5,
      "TranslatorNote": "",
      "Notes": "",
      "LastDate": "2023-04-05T06:31:04.5145641Z",
      "Status": 3,
      "Format": 0
    },
    {
      "Paper": 11,
      "Section": 9,
      "Paragraph": 6,
      "TranslatorNote": "",
      "Notes": "",
      "LastDate": "2013-07-16T11:34:06.71",
      "Status": 1,
      "Format": 3
    },
    {
      "Paper": 11,
      "Section": 9,
      "Paragraph": 7,
      "TranslatorNote": "",
      "Notes": "",
      "LastDate": "2013-07-16T11:34:06.717",
      "Status": 1,
      "Format": 3
    },
    {
      "Paper": 11,
      "Section": 9,
      "Paragraph": 8,
      "TranslatorNote": "",
      "Notes": "",
      "LastDate": "2013-07-16T11:34:06.723",
      "Status": 1,
      "Format": 3
    },
    {
      "Paper": 11,
      "Section": 9,
      "Paragraph": 9,
      "TranslatorNote": "",
      "Notes": "",
      "LastDate": "2013-07-16T11:34:06.73",
      "Status": 1,
      "Format": 3
    }
  ]
}